strarr/__init__.py
strarr-0.1.1.dist-info/METADATA
strarr-0.1.1.dist-info/WHEEL
strarr-0.1.1.dist-info/licenses/LICENSE
strarr-0.1.1.dist-info/RECORD
