Metadata-Version: 2.4
Name: strarr
Version: 0.1.1
Summary: Render iterable of objects or dictionaries into a formatted table string.
Project-URL: Repository, https://github.com/ductorex/strarr
License-File: LICENSE
Requires-Python: >=3.13
